COPYRIGHT
LICENSE
MANIFEST.in
setup.py
tsung2graphite.py
tsung2graphite.egg-info/PKG-INFO
tsung2graphite.egg-info/SOURCES.txt
tsung2graphite.egg-info/dependency_links.txt
tsung2graphite.egg-info/top_level.txt