Metadata-Version: 1.1
Name: tsung2graphite
Version: 0.2.1
Summary: Push tsung log datas to graphite
Home-page: https://gitorious.org/tsung2graphite
Author: Rodolphe Quiédeville
Author-email: rodolphe@quiedeville.org
License: UNKNOWN
Platform: UNKNOWN
Classifier: Development Status :: 4 - Beta
Classifier: Environment :: Web Environment
Classifier: Intended Audience :: Developers
Classifier: Intended Audience :: System Administrators
Classifier: License :: OSI Approved :: GNU General Public License v3 (GPLv3)
Classifier: Programming Language :: Python
Classifier: Operating System :: OS Independent
Classifier: Topic :: System :: Monitoring
